superduper_sqlalchemy/__init__.py
superduper_sqlalchemy/db_helper.py
superduper_sqlalchemy/metadata.py
superduper_sqlalchemy-0.5.8.dist-info/licenses/LICENSE
superduper_sqlalchemy-0.5.8.dist-info/METADATA
superduper_sqlalchemy-0.5.8.dist-info/WHEEL
superduper_sqlalchemy-0.5.8.dist-info/top_level.txt
superduper_sqlalchemy-0.5.8.dist-info/RECORD
