Metadata-Version: 2.4
Name: superduper_sqlalchemy
Version: 0.5.8
Summary: Superduper sqlalchemy is a metadata plugin for Superduper that allows you to store metadata in a SQL database.
Maintainer-email: "superduper.io, Inc." <opensource@superduper.io>
License: 
Project-URL: homepage, https://superduper.io
Project-URL: documentation, https://docs.superduper.io/docs/intro
Project-URL: source, https://github.com/superduper-io/superduper
Keywords: databases,mongodb,data-science,machine-learning,mlops,vector-database,ai
Requires-Python: >=3.10
License-File: LICENSE
Requires-Dist: sqlalchemy>=1.4.0
Provides-Extra: test
Dynamic: license-file
